{"navigationBarTitleText":"","usingComponents":{"simple-loading":"../../components/SimpleLoading","mod-game-list":"../../components/ModGameList","float-download":"../../components/FloatDownload","footer":"../../components/Footer","book-modal":"../../components/BookModal","install-modal":"../../components/InstallModal","pause-modal":"../../components/PauseModal"},"isUsingComponents":true,"skeleton":"","usingDynamicLibs":[],"usingPlugins":[],"usingDependencies":[],"isUsingSJS":false,"_hasVideo":false}